{"orgs":[{"orgId":"225077301031784451", "org":{"name":"ZITADEL"}, "projects":[{"projectId":"225077301031915523", "project":{"name":"ZITADEL"}}], "apiApps":[{"appId":"225077301031981059", "app":{"projectId":"225077301031915523", "name":"Management-API", "authMethodType":"API_AUTH_METHOD_TYPE_PRIVATE_KEY_JWT"}}, {"appId":"225077301032046595", "app":{"projectId":"225077301031915523", "name":"Admin-API", "authMethodType":"API_AUTH_METHOD_TYPE_PRIVATE_KEY_JWT"}}, {"appId":"225077301032112131", "app":{"projectId":"225077301031915523", "name":"Auth-API", "authMethodType":"API_AUTH_METHOD_TYPE_PRIVATE_KEY_JWT"}}], "oidcApps":[{"appId":"225077301032177667", "app":{"projectId":"225077301031915523", "name":"Console", "redirectUris":["http://zitadel-3oss0n.localhost:8888/ui/console/auth/callback", "http://localhost:8888/ui/console/auth/callback"], "responseTypes":["OIDC_RESPONSE_TYPE_CODE"], "grantTypes":["OIDC_GRANT_TYPE_AUTHORIZATION_CODE"], "appType":"OIDC_APP_TYPE_USER_AGENT", "authMethodType":"OIDC_AUTH_METHOD_TYPE_NONE", "postLogoutRedirectUris":["http://zitadel-3oss0n.localhost:8888/ui/console/signedout", "http://localhost:8888/ui/console/signedout"], "devMode":true, "clockSkew":"0s"}}], "humanUsers":[{"userId":"225077301031849987", "user":{"userName":"zitadel-admin@zitadel.localhost", "profile":{"firstName":"zitadel", "lastName":"admin", "displayName":"zitadel admin", "preferredLanguage":"en"}, "email":{"email":"zitadel-admin@zitadel.localhost", "isEmailVerified":true}, "hashedPassword":{"value":"$2a$14$/7eNwrNNPBEvd98eic1hT.Zg2akov8ELQOYYRkX3dy2lzON9vVwY."}}}], "machineUsers":[{"userId":"225079616925126659", "user":{"userName":"export_user", "name":"export_user"}}], "orgMembers":[{"userId":"225077301031849987", "roles":["ORG_OWNER"]}], "projectMembers":[{"projectId":"225077301031915523", "userId":"225077301031849987", "roles":["PROJECT_OWNER"]}, {"projectId":"225073430326722563", "userId":"225073286965477379", "roles":["PROJECT_OWNER"]}], "domains":[{"orgId":"225077301031784451", "domainName":"zitadel.localhost", "isVerified":true, "isPrimary":true}]}, {"orgId":"225073286965411843", "org":{"name":"Office Buddy"}, "loginPolicy":{"allowUsernamePassword":true, "allowExternalIdp":true, "passwordlessType":"PASSWORDLESS_TYPE_ALLOWED", "passwordCheckLifetime":"864000s", "externalLoginCheckLifetime":"864000s", "mfaInitSkipLifetime":"2592000s", "secondFactorCheckLifetime":"64800s", "multiFactorCheckLifetime":"43200s", "secondFactors":["SECOND_FACTOR_TYPE_OTP", "SECOND_FACTOR_TYPE_U2F"], "multiFactors":["MULTI_FACTOR_TYPE_U2F_WITH_VERIFICATION"]}, "projects":[{"projectId":"225073430326722563", "project":{"name":"Office Buddy"}}], "projectRoles":[{"projectId":"225073430326722563", "roleKey":"office_manager", "displayName":"Office Manager"}, {"projectId":"225073430326722563", "roleKey":"super_admin", "displayName":"Super Admin"}, {"projectId":"225073430326722563", "roleKey":"user", "displayName":"User"}], "apiApps":[{"appId":"225079438683983875", "app":{"projectId":"225073430326722563", "name":"API"}}], "oidcApps":[{"appId":"225073771575296003", "app":{"projectId":"225073430326722563", "name":"UI", "redirectUris":["http://localhost:4200"], "responseTypes":["OIDC_RESPONSE_TYPE_CODE"], "grantTypes":["OIDC_GRANT_TYPE_AUTHORIZATION_CODE"], "appType":"OIDC_APP_TYPE_USER_AGENT", "authMethodType":"OIDC_AUTH_METHOD_TYPE_NONE", "postLogoutRedirectUris":["http://localhost:4200"], "clockSkew":"0s"}}], "humanUsers":[{"userId":"225073286965477379", "user":{"userName":"super-admin", "profile":{"firstName":"super", "lastName":"admin", "displayName":"super admin", "preferredLanguage":"und"}, "email":{"email":"super-admin@office-buddy.localhost", "isEmailVerified":true}, "hashedPassword":{"value":"$2a$14$/B7NMvnu5zryeBLnk5nXeu0KlDknTzzH3n4kHtbVaGuRu0lzxq3h2"}}}], "userGrants":[{"userId":"225073286965477379", "projectId":"225073430326722563", "roleKeys":["super_admin"]}], "orgMembers":[{"userId":"225073286965477379", "roles":["ORG_OWNER"]}], "projectMembers":[{"projectId":"225077301031915523", "userId":"225077301031849987", "roles":["PROJECT_OWNER"]}, {"projectId":"225073430326722563", "userId":"225073286965477379", "roles":["PROJECT_OWNER"]}], "domains":[{"orgId":"225073286965411843", "domainName":"localhost"}, {"orgId":"225073286965411843", "domainName":"office-buddy.localhost", "isVerified":true, "isPrimary":true}]}]}